{
  "db_name": "PostgreSQL",
  "query": "\n                INSERT INTO panorama (\n                    media_item_id, is_photosphere, projection_type, horizontal_fov_deg,\n                    vertical_fov_deg, center_yaw_deg, center_pitch_deg\n                )\n                VALUES ($1, $2, $3, $4, $5, $6, $7)\n                ",
  "describe": {
    "columns": [],
    "parameters": {
      "Left": [
        "Varchar",
        "Bool",
        "Text",
        "Float4",
        "Float4",
        "Float4",
        "Float4"
      ]
    },
    "nullable": []
  },
  "hash": "45d24f34f95f93a1605c8f16eefacaaaf413d8975f66eafff1915ded0581b90f"
}
