{
  "db_name": "PostgreSQL",
  "query": "\n        DELETE FROM pending_album_media_items\n        WHERE relative_path = $1\n        RETURNING album_id, remote_user_identity, relative_path\n        ",
  "describe": {
    "columns": [
      {
        "ordinal": 0,
        "name": "album_id",
        "type_info": "Varchar"
      },
      {
        "ordinal": 1,
        "name": "remote_user_identity",
        "type_info": "Text"
      },
      {
        "ordinal": 2,
        "name": "relative_path",
        "type_info": "Text"
      }
    ],
    "parameters": {
      "Left": [
        "Text"
      ]
    },
    "nullable": [
      false,
      false,
      false
    ]
  },
  "hash": "aed20b6fddebdb304bacec58cf863e72594cacdfec91a227f389f266a502f159"
}
