{
  "db_name": "PostgreSQL",
  "query": "\n        INSERT INTO album (id, owner_id, name, description, is_public)\n        VALUES ($1, $2, $3, $4, $5)\n        RETURNING *\n        ",
  "describe": {
    "columns": [
      {
        "ordinal": 0,
        "name": "id",
        "type_info": "Varchar"
      },
      {
        "ordinal": 1,
        "name": "owner_id",
        "type_info": "Int4"
      },
      {
        "ordinal": 2,
        "name": "name",
        "type_info": "Text"
      },
      {
        "ordinal": 3,
        "name": "description",
        "type_info": "Text"
      },
      {
        "ordinal": 4,
        "name": "is_public",
        "type_info": "Bool"
      },
      {
        "ordinal": 5,
        "name": "created_at",
        "type_info": "Timestamptz"
      },
      {
        "ordinal": 6,
        "name": "updated_at",
        "type_info": "Timestamptz"
      }
    ],
    "parameters": {
      "Left": [
        "Varchar",
        "Int4",
        "Text",
        "Text",
        "Bool"
      ]
    },
    "nullable": [
      false,
      false,
      false,
      true,
      false,
      false,
      false
    ]
  },
  "hash": "5ba1293cc0a5f8fee5d933e3edde86c58ac82de1bf9eb9fc262056bbdbadb040"
}
